{
  "protocol_version" : "0.0.6",
  "configuration" : {
    "version" : "(6.12.0.122) (2020-02/c621c35ffa0)",
    "tlc" : "normal",
    "sigsgev" : "altstack",
    "notifications" : "kqueue",
    "architecture" : "amd64",
    "disabled_features" : "none",
    "smallconfig" : "disabled",
    "bigarrays" : "disabled",
    "softdebug" : "enabled",
    "interpreter" : "enabled",
    "llvm_support" : "0",
    "suspend" : "hybrid"
  },
  "memory" : {
    "Resident Size" : "184107008",
    "Virtual Size" : "8991141888",
    "minor_gc_time" : "0",
    "major_gc_time" : "0",
    "minor_gc_count" : "0",
    "major_gc_count" : "0",
    "major_gc_time_concurrent" : "0"
 },
  "failfast_message" : "mscorlib.resources couldn't be found!  Large parts of the BCL won't work!",
  "threads" : [
 {
    "is_managed" : false,
    "offset_free_hash" : "0x0",
    "offset_rich_hash" : "0x0",
    "crashed" : false,
    "native_thread_id" : "0x30cf56000",
    "thread_info_addr" : "0x7fe88a840000",
    "thread_name" : "Finalizer",
    "ctx" : {
      "IP" : "0x7fff2033deba",
      "SP" : "0x30cf55eb8",
      "BP" : "0x30cf55f00"
  },
    "unmanaged_frames" : [
  {
      "is_managed" : "false",
      "native_address" : "0x104313a06",
      "native_offset" : "0x00000"
   }
,
  {
      "is_managed" : "false",
      "native_address" : "0x1044af165",
      "native_offset" : "0x00000"
   }
,
  {
      "is_managed" : "false",
      "native_address" : "0x1044aee97",
      "native_offset" : "0x00000"
   }
,
  {
      "is_managed" : "false",
      "native_address" : "0x10437f9d0",
      "native_offset" : "0x00000"
   }
,
  {
      "is_managed" : "false",
      "native_address" : "0x7fff203b6d7d",
      "native_offset" : "0x00000"
   }
,
  {
      "is_managed" : "false",
      "native_address" : "unregistered"
   }
,
  {
      "is_managed" : "false",
      "native_address" : "0x1044afdad",
      "native_offset" : "0x00000"
   }
,
  {
      "is_managed" : "false",
      "native_address" : "0x7fff20372950",
      "native_offset" : "0x00000"
   }
,
  {
      "is_managed" : "false",
      "native_address" : "0x7fff2036e47b",
      "native_offset" : "0x00000"
   }

  ]
 },
 {
    "is_managed" : true,
    "offset_free_hash" : "0x22cb579ad",
    "offset_rich_hash" : "0x22cb58297",
    "crashed" : true,
    "native_thread_id" : "0x204a2fe00",
    "thread_info_addr" : "0x7fe88a80be00",
    "thread_name" : "tid_203",
    "ctx" : {
      "IP" : "0x7fff20344462",
      "SP" : "0x30ccd0938",
      "BP" : "0x30ccd0960"
  },
    "managed_frames" : [
  {
      "is_managed" : "false",
      "native_address" : "unregistered"
   }
,
  {
      "is_managed" : "true",
      "guid" : "36514B14-425C-4337-B446-653C547AA9C3",
      "token" : "0x00000",
      "native_offset" : "0x0",
      "filename" : "mscorlib.dll",
      "sizeofimage" : "0x472000",
      "timestamp" : "0xd38c2365",
      "il_offset" : "0x00000"
   }
,
  {
      "is_managed" : "true",
      "guid" : "6D5C9385-D6D2-418F-952F-CA7F4B0B0D1C",
      "token" : "0x6000184",
      "native_offset" : "0x0",
      "filename" : "zft.exe",
      "sizeofimage" : "0x12000",
      "timestamp" : "0x605b3463",
      "il_offset" : "0x00020"
   }
,
  {
      "is_managed" : "true",
      "guid" : "6D5C9385-D6D2-418F-952F-CA7F4B0B0D1C",
      "token" : "0x600008b",
      "native_offset" : "0x0",
      "filename" : "zft.exe",
      "sizeofimage" : "0x12000",
      "timestamp" : "0x605b3463",
      "il_offset" : "0x001ce"
   }
,
  {
      "is_managed" : "true",
      "guid" : "6D5C9385-D6D2-418F-952F-CA7F4B0B0D1C",
      "token" : "0x6000150",
      "native_offset" : "0x0",
      "filename" : "zft.exe",
      "sizeofimage" : "0x12000",
      "timestamp" : "0x605b3463",
      "il_offset" : "0x00000"
   }
,
  {
      "is_managed" : "true",
      "guid" : "6D5C9385-D6D2-418F-952F-CA7F4B0B0D1C",
      "token" : "0x600006b",
      "native_offset" : "0x0",
      "filename" : "zft.exe",
      "sizeofimage" : "0x12000",
      "timestamp" : "0x605b3463",
      "il_offset" : "0x006c6"
   }
,
  {
      "is_managed" : "true",
      "guid" : "6D5C9385-D6D2-418F-952F-CA7F4B0B0D1C",
      "token" : "0x6000002",
      "native_offset" : "0x0",
      "filename" : "zft.exe",
      "sizeofimage" : "0x12000",
      "timestamp" : "0x605b3463",
      "il_offset" : "0x0000c"
   }
,
  {
      "is_managed" : "true",
      "guid" : "36514B14-425C-4337-B446-653C547AA9C3",
      "token" : "0x00000",
      "native_offset" : "0x0",
      "filename" : "mscorlib.dll",
      "sizeofimage" : "0x472000",
      "timestamp" : "0xd38c2365",
      "il_offset" : "0x0002a"
   }

  ],
  "unmanaged_frames" : [
 {
    "is_managed" : "false",
    "native_address" : "0x104313a06",
    "native_offset" : "0x00000"
  }
,
 {
    "is_managed" : "false",
    "native_address" : "0x1044af165",
    "native_offset" : "0x00000"
  }
,
 {
    "is_managed" : "false",
    "native_address" : "0x1044af7da",
    "native_offset" : "0x00000"
  }
,
 {
    "is_managed" : "false",
    "native_address" : "0x104380a97",
    "native_offset" : "0x00000"
  }
,
 {
    "is_managed" : "false",
    "native_address" : "0x10431869e",
    "native_offset" : "0x00000"
  }
,
 {
    "is_managed" : "false",
    "native_address" : "0x10437fd8f",
    "native_offset" : "0x00000"
  }
,
 {
    "is_managed" : "false",
    "native_address" : "0x7fff203b6d7d",
    "native_offset" : "0x00000"
  }
,
 {
    "is_managed" : "false",
    "native_address" : "0x48a45ef40",
    "native_offset" : "0x00000"
  }
,
 {
    "is_managed" : "false",
    "native_address" : "0x7fff202c5720",
    "native_offset" : "0x00000"
  }
,
 {
    "is_managed" : "false",
    "native_address" : "0x10442e4b7",
    "native_offset" : "0x00000"
  }
,
 {
    "is_managed" : "false",
    "native_address" : "0x1044345a2",
    "native_offset" : "0x00000"
  }
,
 {
    "is_managed" : "true",
    "guid" : "36514B14-425C-4337-B446-653C547AA9C3",
    "token" : "0x00000",
    "native_offset" : "0x0",
    "filename" : "mscorlib.dll",
    "sizeofimage" : "0x472000",
    "timestamp" : "0xd38c2365",
    "il_offset" : "0x00000"
  }
,
 {
    "is_managed" : "true",
    "guid" : "(null)",
    "token" : "0x00000",
    "native_offset" : "0x0",
    "filename" : "(null)",
    "sizeofimage" : "0x0",
    "timestamp" : "0x0",
    "il_offset" : "0x00000"
  }
,
 {
    "is_managed" : "true",
    "guid" : "(null)",
    "token" : "0x00000",
    "native_offset" : "0x0",
    "filename" : "(null)",
    "sizeofimage" : "0x0",
    "timestamp" : "0x0",
    "il_offset" : "0x00000"
  }
,
 {
    "is_managed" : "true",
    "guid" : "(null)",
    "token" : "0x00000",
    "native_offset" : "0x0",
    "filename" : "(null)",
    "sizeofimage" : "0x0",
    "timestamp" : "0x0",
    "il_offset" : "0x00000"
  }
,
 {
    "is_managed" : "true",
    "guid" : "6D5C9385-D6D2-418F-952F-CA7F4B0B0D1C",
    "token" : "0x6000002",
    "native_offset" : "0x0",
    "filename" : "zft.exe",
    "sizeofimage" : "0x12000",
    "timestamp" : "0x605b3463",
    "il_offset" : "0x00000"
  }
,
 {
    "is_managed" : "false",
    "native_address" : "0x104275962",
    "native_offset" : "0x00000"
  }
,
 {
    "is_managed" : "false",
    "native_address" : "0x104484f97",
    "native_offset" : "0x00000"
  }
,
 {
    "is_managed" : "false",
    "native_address" : "0x10448d45e",
    "native_offset" : "0x00000"
  }
,
 {
    "is_managed" : "false",
    "native_address" : "0x1042d5e1e",
    "native_offset" : "0x00000"
  }
,
 {
    "is_managed" : "false",
    "native_address" : "0x1042d9085",
    "native_offset" : "0x00000"
  }
,
 {
    "is_managed" : "false",
    "native_address" : "0x104265178",
    "native_offset" : "0x00000"
  }
,
 {
    "is_managed" : "false",
    "native_address" : "0x7fff2038d621",
    "native_offset" : "0x00000"
  }
,
 {
    "is_managed" : "false",
    "native_address" : "0x2",
    "native_offset" : "0x00000"
  }

 ]
}
]
}